django_relay_endpoint/__init__.py
django_relay_endpoint/apps.py
django_relay_endpoint/tests.py
django_relay_endpoint/configurators/__init__.py
django_relay_endpoint/configurators/field_conversions.py
django_relay_endpoint/configurators/fields.py
django_relay_endpoint/configurators/node.py
django_relay_endpoint/configurators/object_type_configurator.py
django_relay_endpoint/configurators/object_types.py
django_relay_endpoint/configurators/permissions.py
django_relay_endpoint/configurators/queries_configurator.py
django_relay_endpoint/configurators/schema.py
django_relay_endpoint/configurators/mutation_configurators/__init__.py
django_relay_endpoint/configurators/mutation_configurators/abstract_mutation_class_configurator.py
django_relay_endpoint/configurators/mutation_configurators/create_mutation_configurator.py
django_relay_endpoint/configurators/mutation_configurators/delete_mutation_configurator.py
django_relay_endpoint/configurators/mutation_configurators/input_object_type_configurator.py
django_relay_endpoint/configurators/mutation_configurators/update_mutation_configurator.py
django_relay_endpoint/management/__init__.py
django_relay_endpoint/management/commands/__init__.py
django_relay_endpoint/management/commands/dre-from-json.py
django_relay_endpoint/management/commands/dre-from-model.py
django_relay_endpoint/management/commands/dre-from-models.py
django_relay_endpoint/management/commands/dre-from-schema.py
django_relay_endpoint/management/commands/boilerplate/__init__.py
django_relay_endpoint/management/commands/boilerplate/boilers.py
django_relay_endpoint/management/commands/boilerplate/types.pyi
django_relay_endpoint/management/commands/boilerplate/utils.py
django_relay_endpoint-2.0.0.dist-info/LICENSE
django_relay_endpoint-2.0.0.dist-info/METADATA
django_relay_endpoint-2.0.0.dist-info/WHEEL
django_relay_endpoint-2.0.0.dist-info/top_level.txt
django_relay_endpoint-2.0.0.dist-info/RECORD
